pynumbpkg/__init__.py
pynumbpkg/__main__.py
pynumbpkg/config.txt
pynumbpkg/feed.py
pynumbpkg/viewer.py
pynumbpkg-1.3.0.dist-info/METADATA
pynumbpkg-1.3.0.dist-info/WHEEL
pynumbpkg-1.3.0.dist-info/entry_points.txt
pynumbpkg-1.3.0.dist-info/top_level.txt
pynumbpkg-1.3.0.dist-info/RECORD
